figenv.py
figenv-1.5.1.dist-info/licenses/LICENSE
figenv-1.5.1.dist-info/METADATA
figenv-1.5.1.dist-info/WHEEL
figenv-1.5.1.dist-info/top_level.txt
figenv-1.5.1.dist-info/RECORD
