Metadata-Version: 2.4
Name: figenv
Version: 1.5.1
Summary: Metaclass for handling configuration class objects using environment variables
Home-page: https://github.com/gtmanfred/figenv
Author: Daniel Wallace
Author-email: daniel@gtmanfred.com
License: APACHE-2.0
Project-URL: Repository, https://github.com/gtmanfred/figenv
Project-URL: Docs, https://figenv.readthedocs.org
Classifier: Development Status :: 4 - Beta
Classifier: Topic :: Software Development :: Libraries :: Python Modules
Classifier: License :: OSI Approved :: Apache Software License
Classifier: Operating System :: OS Independent
Classifier: Programming Language :: Python :: 3.6
Classifier: Programming Language :: Python :: 3.7
Classifier: Programming Language :: Python :: 3.8
Classifier: Programming Language :: Python :: 3.9
Classifier: Programming Language :: Python :: 3.10
Requires-Python: >=3.6
License-File: LICENSE
Provides-Extra: tests
Requires-Dist: coverage; extra == "tests"
Requires-Dist: codecov; extra == "tests"
Requires-Dist: black; extra == "tests"
Requires-Dist: unittest-xml-reporting; extra == "tests"
Provides-Extra: docs
Requires-Dist: sphinx; extra == "docs"
Requires-Dist: sphinx-rtd-theme; extra == "docs"
Dynamic: license-file
